myo/__init__.py
myo/commands.py
myo/constants.py
myo/core.py
myo/profile.py
myo/types.py
myo/utils.py
myo/version.py
dl_myo-1.1.8.dist-info/LICENSE
dl_myo-1.1.8.dist-info/METADATA
dl_myo-1.1.8.dist-info/WHEEL
dl_myo-1.1.8.dist-info/RECORD
