Metadata-Version: 2.1
Name: dl-myo
Version: 1.1.8
Summary: Yet another MyoConnect alternative without dongles
License: GPLv3
Author: Iori Mizutani
Author-email: iomz@sazanka.io
Requires-Python: >=3.8,<4.0
Classifier: License :: Other/Proprietary License
Classifier: Programming Language :: Python :: 3
Classifier: Programming Language :: Python :: 3.8
Classifier: Programming Language :: Python :: 3.9
Classifier: Programming Language :: Python :: 3.10
Classifier: Programming Language :: Python :: 3.11
Requires-Dist: aiohttp (>=3.8.4,<4.0.0)
Requires-Dist: bleak (>=0.20.2,<0.21.0)
Requires-Dist: influxdb-client[ciso] (>=1.36.1,<2.0.0)
